whatsapp_business_api_is/__init__.py
whatsapp_business_api_is/admin.py
whatsapp_business_api_is/apps.py
whatsapp_business_api_is/bot_functions.py
whatsapp_business_api_is/conf.py
whatsapp_business_api_is/exceptions.py
whatsapp_business_api_is/messages.py
whatsapp_business_api_is/models.py
whatsapp_business_api_is/singelton.py
whatsapp_business_api_is/tasks.py
whatsapp_business_api_is/urls.py
whatsapp_business_api_is/user_msg.py
whatsapp_business_api_is/utils.py
whatsapp_business_api_is/views.py
whatsapp_business_api_is/management/__init__.py
whatsapp_business_api_is/management/commands/__init__.py
whatsapp_business_api_is/management/commands/register_360dialog_webhook.py
whatsapp_business_api_is/migrations/0001_initial.py
whatsapp_business_api_is/migrations/0002_wauser_disable_bot_wauser_failure_count.py
whatsapp_business_api_is/migrations/__init__.py
whatsapp_business_api_is/tests/__init__.py
whatsapp_business_api_is/tests/test_bot_functions.py
django_whatsapp_business_api_is-0.1.25.dist-info/LICENSE
django_whatsapp_business_api_is-0.1.25.dist-info/METADATA
django_whatsapp_business_api_is-0.1.25.dist-info/WHEEL
django_whatsapp_business_api_is-0.1.25.dist-info/top_level.txt
django_whatsapp_business_api_is-0.1.25.dist-info/RECORD
