Metadata-Version: 2.1
Name: django-whatsapp-business-api-is
Version: 0.1.25
Summary: Django Whatsapp Business Api Infrastructure
Home-page: https://github.com/roigreenberg/django-whatsapp-business-api-is
License: BSD-2-Clause
Classifier: Development Status :: 4 - Beta
Classifier: Environment :: Web Environment
Classifier: Intended Audience :: Developers
Classifier: License :: OSI Approved :: BSD License
Classifier: Operating System :: OS Independent
Classifier: Programming Language :: Python
Classifier: Programming Language :: Python :: 3
Classifier: Programming Language :: Python :: 3 :: Only
Classifier: Programming Language :: Python :: 3.10
Classifier: Topic :: Software Development :: Libraries :: Python Modules
Requires-Python: >=3.10
License-File: LICENSE
Requires-Dist: Django (>=4.0.3)
